{
  "results": [
    {
      "name": "FP32_Baseline",
      "category": "baseline",
      "accuracy": 97.64,
      "avg_weight_bits": 32.0,
      "avg_activation_bits": 32.0,
      "bops_gbops": 11241.05,
      "calibration_time": 0.0,
      "evaluation_time": 18.72,
      "total_time": 18.72
    },
    {
      "name": "W8/A8",
      "category": "uniform",
      "accuracy": 97.24,
      "avg_weight_bits": 8.0,
      "avg_activation_bits": 8.0,
      "bops_gbops": 702.57,
      "calibration_time": 4.16,
      "evaluation_time": 24.93,
      "total_time": 29.78,
      "accuracy_drop": 0.4,
      "bops_reduction": 16.0
    },
    {
      "name": "W8/A6",
      "category": "uniform",
      "accuracy": 67.15,
      "avg_weight_bits": 8.0,
      "avg_activation_bits": 6.0,
      "bops_gbops": 526.92,
      "calibration_time": 3.35,
      "evaluation_time": 25.23,
      "total_time": 30.2,
      "accuracy_drop": 30.49,
      "bops_reduction": 21.33
    },
    {
      "name": "W8/A4",
      "category": "uniform",
      "accuracy": 10.75,
      "avg_weight_bits": 8.0,
      "avg_activation_bits": 4.0,
      "bops_gbops": 351.28,
      "calibration_time": 3.9,
      "evaluation_time": 24.94,
      "total_time": 30.11,
      "accuracy_drop": 86.89,
      "bops_reduction": 32.0
    },
    {
      "name": "W8/A2",
      "category": "uniform",
      "accuracy": 10.0,
      "avg_weight_bits": 8.0,
      "avg_activation_bits": 2.0,
      "bops_gbops": 175.64,
      "calibration_time": 3.94,
      "evaluation_time": 24.24,
      "total_time": 30.02,
      "accuracy_drop": 87.64,
      "bops_reduction": 64.0
    },
    {
      "name": "W6/A8",
      "category": "uniform",
      "accuracy": 96.1,
      "avg_weight_bits": 6.0,
      "avg_activation_bits": 8.0,
      "bops_gbops": 526.92,
      "calibration_time": 4.32,
      "evaluation_time": 24.76,
      "total_time": 30.69,
      "accuracy_drop": 1.54,
      "bops_reduction": 21.33
    },
    {
      "name": "W6/A6",
      "category": "uniform",
      "accuracy": 79.24,
      "avg_weight_bits": 6.0,
      "avg_activation_bits": 6.0,
      "bops_gbops": 395.19,
      "calibration_time": 4.13,
      "evaluation_time": 24.74,
      "total_time": 30.04,
      "accuracy_drop": 18.4,
      "bops_reduction": 28.44
    },
    {
      "name": "W6/A4",
      "category": "uniform",
      "accuracy": 10.27,
      "avg_weight_bits": 6.0,
      "avg_activation_bits": 4.0,
      "bops_gbops": 263.46,
      "calibration_time": 4.54,
      "evaluation_time": 24.91,
      "total_time": 31.12,
      "accuracy_drop": 87.37,
      "bops_reduction": 42.67
    },
    {
      "name": "W6/A2",
      "category": "uniform",
      "accuracy": 10.0,
      "avg_weight_bits": 6.0,
      "avg_activation_bits": 2.0,
      "bops_gbops": 131.73,
      "calibration_time": 3.86,
      "evaluation_time": 24.35,
      "total_time": 29.79,
      "accuracy_drop": 87.64,
      "bops_reduction": 85.33
    },
    {
      "name": "W4/A8",
      "category": "uniform",
      "accuracy": 10.13,
      "avg_weight_bits": 4.0,
      "avg_activation_bits": 8.0,
      "bops_gbops": 351.28,
      "calibration_time": 4.55,
      "evaluation_time": 24.55,
      "total_time": 30.56,
      "accuracy_drop": 87.51,
      "bops_reduction": 32.0
    },
    {
      "name": "W4/A6",
      "category": "uniform",
      "accuracy": 9.57,
      "avg_weight_bits": 4.0,
      "avg_activation_bits": 6.0,
      "bops_gbops": 263.46,
      "calibration_time": 3.63,
      "evaluation_time": 24.89,
      "total_time": 29.11,
      "accuracy_drop": 88.07,
      "bops_reduction": 42.67
    },
    {
      "name": "W4/A4",
      "category": "uniform",
      "accuracy": 11.36,
      "avg_weight_bits": 4.0,
      "avg_activation_bits": 4.0,
      "bops_gbops": 175.64,
      "calibration_time": 4.38,
      "evaluation_time": 25.01,
      "total_time": 31.16,
      "accuracy_drop": 86.28,
      "bops_reduction": 64.0
    },
    {
      "name": "W4/A2",
      "category": "uniform",
      "accuracy": 10.52,
      "avg_weight_bits": 4.0,
      "avg_activation_bits": 2.0,
      "bops_gbops": 87.82,
      "calibration_time": 3.08,
      "evaluation_time": 24.96,
      "total_time": 29.66,
      "accuracy_drop": 87.12,
      "bops_reduction": 128.0
    },
    {
      "name": "W2/A8",
      "category": "uniform",
      "accuracy": 10.0,
      "avg_weight_bits": 2.0,
      "avg_activation_bits": 8.0,
      "bops_gbops": 175.64,
      "calibration_time": 4.11,
      "evaluation_time": 25.18,
      "total_time": 30.93,
      "accuracy_drop": 87.64,
      "bops_reduction": 64.0
    },
    {
      "name": "W2/A6",
      "category": "uniform",
      "accuracy": 10.0,
      "avg_weight_bits": 2.0,
      "avg_activation_bits": 6.0,
      "bops_gbops": 131.73,
      "calibration_time": 3.97,
      "evaluation_time": 24.98,
      "total_time": 30.6,
      "accuracy_drop": 87.64,
      "bops_reduction": 85.33
    },
    {
      "name": "W2/A4",
      "category": "uniform",
      "accuracy": 10.0,
      "avg_weight_bits": 2.0,
      "avg_activation_bits": 4.0,
      "bops_gbops": 87.82,
      "calibration_time": 4.44,
      "evaluation_time": 25.41,
      "total_time": 31.54,
      "accuracy_drop": 87.64,
      "bops_reduction": 128.0
    },
    {
      "name": "W2/A2",
      "category": "uniform",
      "accuracy": 10.0,
      "avg_weight_bits": 2.0,
      "avg_activation_bits": 2.0,
      "bops_gbops": 43.91,
      "calibration_time": 4.17,
      "evaluation_time": 23.06,
      "total_time": 28.43,
      "accuracy_drop": 87.64,
      "bops_reduction": 256.0
    },
    {
      "name": "W-Mixed/A8",
      "category": "mixed_weights",
      "accuracy": 74.03,
      "avg_weight_bits": 5.17,
      "avg_activation_bits": 8.0,
      "bops_gbops": 526.87,
      "calibration_time": 3.08,
      "evaluation_time": 19.83,
      "total_time": 23.78,
      "accuracy_drop": 23.61,
      "bops_reduction": 21.34
    },
    {
      "name": "W-Mixed/A6",
      "category": "mixed_weights",
      "accuracy": 40.35,
      "avg_weight_bits": 5.17,
      "avg_activation_bits": 6.0,
      "bops_gbops": 395.16,
      "calibration_time": 3.26,
      "evaluation_time": 19.37,
      "total_time": 23.14,
      "accuracy_drop": 57.29,
      "bops_reduction": 28.45
    },
    {
      "name": "W-Mixed/A4",
      "category": "mixed_weights",
      "accuracy": 10.05,
      "avg_weight_bits": 5.17,
      "avg_activation_bits": 4.0,
      "bops_gbops": 263.44,
      "calibration_time": 3.03,
      "evaluation_time": 19.74,
      "total_time": 23.27,
      "accuracy_drop": 87.59,
      "bops_reduction": 42.67
    },
    {
      "name": "W-Mixed/A2",
      "category": "mixed_weights",
      "accuracy": 10.0,
      "avg_weight_bits": 5.17,
      "avg_activation_bits": 2.0,
      "bops_gbops": 131.72,
      "calibration_time": 3.25,
      "evaluation_time": 19.55,
      "total_time": 23.3,
      "accuracy_drop": 87.64,
      "bops_reduction": 85.34
    },
    {
      "name": "W8/A-Mixed",
      "category": "mixed_activations",
      "accuracy": 90.49,
      "avg_weight_bits": 8.0,
      "avg_activation_bits": 7.02,
      "bops_gbops": 527.46,
      "calibration_time": 3.43,
      "evaluation_time": 19.47,
      "total_time": 23.91,
      "accuracy_drop": 7.15,
      "bops_reduction": 21.31
    },
    {
      "name": "W6/A-Mixed",
      "category": "mixed_activations",
      "accuracy": 88.83,
      "avg_weight_bits": 6.0,
      "avg_activation_bits": 7.02,
      "bops_gbops": 395.59,
      "calibration_time": 3.36,
      "evaluation_time": 19.18,
      "total_time": 23.68,
      "accuracy_drop": 8.81,
      "bops_reduction": 28.42
    },
    {
      "name": "W4/A-Mixed",
      "category": "mixed_activations",
      "accuracy": 9.02,
      "avg_weight_bits": 4.0,
      "avg_activation_bits": 7.02,
      "bops_gbops": 263.73,
      "calibration_time": 3.4,
      "evaluation_time": 19.55,
      "total_time": 24.33,
      "accuracy_drop": 88.62,
      "bops_reduction": 42.62
    },
    {
      "name": "W-Mixed/A-Mixed",
      "category": "fully_mixed",
      "accuracy": 47.82,
      "avg_weight_bits": 5.17,
      "avg_activation_bits": 7.02,
      "bops_gbops": 395.62,
      "calibration_time": 3.14,
      "evaluation_time": 19.72,
      "total_time": 24.19,
      "accuracy_drop": 49.82,
      "bops_reduction": 28.41
    }
  ],
  "completed": [
    "W4/A6",
    "W2/A6",
    "W4/A4",
    "W8/A-Mixed",
    "W-Mixed/A8",
    "W-Mixed/A-Mixed",
    "FP32_Baseline",
    "W8/A8",
    "W6/A8",
    "W6/A2",
    "W8/A2",
    "W6/A-Mixed",
    "W2/A8",
    "W6/A4",
    "W4/A-Mixed",
    "W8/A6",
    "W-Mixed/A2",
    "W6/A6",
    "W-Mixed/A4",
    "W4/A2",
    "W2/A2",
    "W2/A4",
    "W8/A4",
    "W-Mixed/A6",
    "W4/A8"
  ]
}